moleculerize/__init__.py
moleculerize/data/molecule.yml.j2
moleculerize-1.1.0.dist-info/LICENSE
moleculerize-1.1.0.dist-info/METADATA
moleculerize-1.1.0.dist-info/WHEEL
moleculerize-1.1.0.dist-info/entry_points.txt
moleculerize-1.1.0.dist-info/top_level.txt
moleculerize-1.1.0.dist-info/RECORD
