Metadata-Version: 2.1
Name: moleculerize
Version: 1.1.0
Summary: Build molecule config files from an Ansible dynamic inventory file
Home-page: https://github.com/rcbops/moleculerize
Author: rcbops
Author-email: rpc-automation@rackspace.com
License: Apache Software License 2.0
Keywords: moleculerize
Platform: UNKNOWN
Classifier: Development Status :: 2 - Pre-Alpha
Classifier: Intended Audience :: Developers
Classifier: License :: OSI Approved :: Apache Software License
Classifier: Natural Language :: English
Classifier: Programming Language :: Python :: 2
Classifier: Programming Language :: Python :: 2.7
Classifier: Programming Language :: Python :: 3
Classifier: Programming Language :: Python :: 3.5
Classifier: Programming Language :: Python :: 3.6
Requires-Python: >=2.7, !=3.0.*, !=3.1.*, !=3.2.*, !=3.3.*
Requires-Dist: Click (>=6.0)
Requires-Dist: jinja2
